linelog2py/__init__.py
linelog2py/category.py
linelog2py/message.py
linelog2py/reader.py
linelog2py-0.1.6.dist-info/LICENSE
linelog2py-0.1.6.dist-info/METADATA
linelog2py-0.1.6.dist-info/WHEEL
linelog2py-0.1.6.dist-info/top_level.txt
linelog2py-0.1.6.dist-info/RECORD
