Metadata-Version: 2.1
Name: linelog2py
Version: 0.1.6
Summary: linelog2py: import LINE Talk History
Home-page: https://github.com/jyu0414/linelog2py
Download-URL: https://github.com/jyu0414/linelog2py
Author: Yuji Sasaki
Author-email: yuji@sasaki.dev
Maintainer: Yuji Sasaki
Maintainer-email: yuji@sasaki.dev
License: MIT License
Classifier: Development Status :: 2 - Pre-Alpha
Classifier: Intended Audience :: Science/Research
Classifier: License :: OSI Approved :: MIT License
Classifier: Programming Language :: Python :: 3
Classifier: Programming Language :: Python :: 3.6
Classifier: Programming Language :: Python :: 3.7
Classifier: Programming Language :: Python :: 3.8
Classifier: Programming Language :: Python :: 3.9
Classifier: Programming Language :: Python :: 3 :: Only
Classifier: Topic :: Scientific/Engineering :: Information Analysis
Classifier: Topic :: Text Editors :: Text Processing
Classifier: Topic :: Text Editors :: Word Processors
Requires-Python: >=3.6
License-File: LICENSE
